{
  "inclusionTestßjsonld,promiz°global.btoa": "NO_CONFLICT",
  "inclusionTestßpromiz,jsonld,jsonld°global.btoa": "NO_CONFLICT",
  "inclusionTestßjsonld,promiz,promiz°global.btoa": "NO_CONFLICT",
  "inclusionTestßpromiz,jsonld,promiz°global.btoa": "NO_CONFLICT",
  "inclusionTestßjsonld,promiz,promiz,jsonld°global.btoa": "NO_CONFLICT",
  "inclusionTestßjsonld,promiz,jsonld°global.btoa": "RAN TOO LONG > 120000 ms",
  "typeTestßjsonld,promiz°global.btoa": "NO_CONFLICT",
  "typeTestßjsonld,promiz,jsonld°global.btoa": "NO_CONFLICT",
  "typeTestßpromiz,jsonld,jsonld°global.btoa": "NO_CONFLICT",
  "typeTestßjsonld,promiz,promiz°global.btoa": "NO_CONFLICT",
  "typeTestßpromiz,jsonld,promiz°global.btoa": "NO_CONFLICT",
  "typeTestßjsonld,promiz,promiz,jsonld°global.btoa": "NO_CONFLICT",
  "value-test-functionsßjsonld,promiz,jsonld°global.btoa": "NOT SURE - Tests could not be generated for both",
  "value-test-functionsßjsonld,promiz°global.btoa": "NOT SURE - Tests could not be generated for both",
  "value-test-functionsßpromiz,jsonld,promiz°global.btoa": "NOT SURE - Tests could not be generated for both",
  "value-test-functionsßjsonld,promiz,promiz°global.btoa": "NOT SURE - Tests could not be generated for both",
  "value-test-functionsßpromiz,jsonld,jsonld°global.btoa": "NOT SURE - Tests could not be generated for both",
  "value-test-functionsßjsonld,promiz,promiz,jsonld°global.btoa": "NOT SURE - Tests could not be generated for both"
}