{
  "inclusionTestßjsonld,promiz,jsonld°global.onafterprint": "NO_CONFLICT",
  "inclusionTestßjsonld,promiz°global.onafterprint": "NO_CONFLICT",
  "inclusionTestßpromiz,jsonld,promiz°global.onafterprint": "NO_CONFLICT",
  "inclusionTestßpromiz,jsonld,jsonld°global.onafterprint": "NO_CONFLICT",
  "inclusionTestßjsonld,promiz,promiz,jsonld°global.onafterprint": "NO_CONFLICT",
  "inclusionTestßjsonld,promiz,promiz°global.onafterprint": "NO_CONFLICT",
  "typeTestßjsonld,promiz°global.onafterprint": "NO_CONFLICT",
  "typeTestßjsonld,promiz,jsonld°global.onafterprint": "NO_CONFLICT",
  "typeTestßpromiz,jsonld,jsonld°global.onafterprint": "NO_CONFLICT",
  "typeTestßjsonld,promiz,promiz°global.onafterprint": "NO_CONFLICT",
  "typeTestßpromiz,jsonld,promiz°global.onafterprint": "NO_CONFLICT",
  "typeTestßjsonld,promiz,promiz,jsonld°global.onafterprint": "NO_CONFLICT",
  "value-test-non-functionsßpromiz,jsonld,jsonld°global.onafterprint": "NO_CONFLICT",
  "value-test-non-functionsßjsonld,promiz°global.onafterprint": "NO_CONFLICT",
  "value-test-non-functionsßjsonld,promiz,jsonld°global.onafterprint": "NO_CONFLICT",
  "value-test-non-functionsßjsonld,promiz,promiz°global.onafterprint": "NO_CONFLICT",
  "value-test-non-functionsßpromiz,jsonld,promiz°global.onafterprint": "NO_CONFLICT",
  "value-test-non-functionsßjsonld,promiz,promiz,jsonld°global.onafterprint": "NO_CONFLICT"
}